{
    "name": "Tonya Monroe",
    "age": 63,
    "address": {
        "street": "Mitchell Groves",
        "city": "Oliviaside",
        "state": "Colorado",
        "zip": "13156"
    },
    "contact": {
        "phone": "2262966889",
        "servicePhone": "800014438"
    },
    "birthday": "1962-07-03",
    "ip": "96.124.59.18",
    "foo": "bar",
    "profile": {
        "about": "Stage fight traditional phone course region. Loss data need side. Member piece growth and sure data.\nElse weight wrong. Couple north share between apply.",
        "bio": "Upon into out your. Action ability role local tough reveal nearly.\nSeveral simple easy against environment economy. Billion prepare store glass road."
    },
    "currency": [
        "FKP",
        "Falkland Islands pound"
    ]
}